aws_proton_template_helper-10.0.2.dist-info/licenses/LICENSE
opensearchpy/__init__.py
opensearchpy/core.py
aws_proton_template_helper-10.0.2.dist-info/METADATA
aws_proton_template_helper-10.0.2.dist-info/WHEEL
aws_proton_template_helper-10.0.2.dist-info/top_level.txt
aws_proton_template_helper-10.0.2.dist-info/RECORD
