Metadata-Version: 2.4
Name: aws-proton-template-helper
Version: 10.0.2
Summary: Experimental Python package for research and educational purposes.
Author-email: Ashutosh <ashutosh.dutta@adsec.in>
License: MIT
Project-URL: Homepage, https://adsec.in
Classifier: Programming Language :: Python :: 3
Classifier: License :: OSI Approved :: MIT License
Classifier: Operating System :: OS Independent
Requires-Python: >=3.8
License-File: LICENSE
Dynamic: license-file
